LICENSE
MANIFEST.in
readme.md
requirements.txt
setup.py
ebs_web/__init__.py
ebs_web/app.py
ebs_web/celery.py
ebs_web/error.py
ebs_web/helper.py
ebs_web/http_status.py
ebs_web/log.py
ebs_web/setting.py
ebs_web/site_setting.py
ebs_web/version.py
ebs_web.egg-info/PKG-INFO
ebs_web.egg-info/SOURCES.txt
ebs_web.egg-info/dependency_links.txt
ebs_web.egg-info/not-zip-safe
ebs_web.egg-info/requires.txt
ebs_web.egg-info/top_level.txt