Metadata-Version: 1.1
Name: ebs-web
Version: 0.0.1
Summary: A web framwork to create web application
Home-page: UNKNOWN
Author: Wang Feng (Felix)
Author-email: wangfelix87@gmail.com
License: UNKNOWN
Platform: UNKNOWN
Classifier: Framework :: Flask
Classifier: Environment :: Web Environment
Classifier: Intended Audience :: Developers
Classifier: Operating System :: OS Independent
Classifier: Programming Language :: Python :: 2 :: Only
Classifier: Topic :: Internet :: WWW/HTTP :: Dynamic Content
Classifier: Topic :: Software Development :: Libraries :: Python Modules
